json_easy/__init__.py
json_easy-1.0.dist-info/METADATA
json_easy-1.0.dist-info/WHEEL
json_easy-1.0.dist-info/top_level.txt
json_easy-1.0.dist-info/RECORD
