Metadata-Version: 2.1
Name: json-easy
Version: 1.0
Summary: Json DB's made easy
Home-page: https://github.com/ConnorTippets/json-easy/
Author: meiscool466
License: MIT
Keywords: json,db,easy
Platform: UNKNOWN
Classifier: Development Status :: 3 - Alpha
Classifier: Intended Audience :: Developers
Classifier: License :: OSI Approved :: MIT License
Classifier: Natural Language :: English
Classifier: Programming Language :: Python :: 3 :: Only
Requires-Python: >=3.8
